NERO/Core.py
NERO/__init__.py
NERO/annotation_results.txt
NERO/corpus.py
NERO_nlp-0.0.8.dist-info/METADATA
NERO_nlp-0.0.8.dist-info/WHEEL
NERO_nlp-0.0.8.dist-info/top_level.txt
NERO_nlp-0.0.8.dist-info/RECORD
