Metadata-Version: 2.1
Name: NERO-nlp
Version: 0.0.8
Summary: A biomedical Named Entity (Recognition) Ontology
Home-page: UNKNOWN
Author: Bohdan Khomtchouk
Author-email: bohdan@uchicago.edu
License: UNKNOWN
Platform: UNKNOWN
Classifier: Programming Language :: Python :: 3
Classifier: License :: OSI Approved :: MIT License
Classifier: Operating System :: OS Independent
Requires-Python: >=3.6
